README.md
setup.py
nnaudio/__init__.py
nnaudio/nnaudio.py
nnaudio_GovGPT.egg-info/PKG-INFO
nnaudio_GovGPT.egg-info/SOURCES.txt
nnaudio_GovGPT.egg-info/dependency_links.txt
nnaudio_GovGPT.egg-info/requires.txt
nnaudio_GovGPT.egg-info/top_level.txt