Metadata-Version: 2.1
Name: nnaudio-GovGPT
Version: 0.1.0
Summary: A library for optimizing audio processing parameters using differential evolution.
Home-page: UNKNOWN
Author: Soumyajit Sen Sharma
Author-email: soumyajit94298@gmal.com
License: MIT
Platform: UNKNOWN
Classifier: Programming Language :: Python :: 3
Classifier: License :: OSI Approved :: MIT License
Classifier: Operating System :: OS Independent
Requires-Python: >=3.6
